pycea-0.0.2.dist-info/RECORD
pycea-0.0.2.dist-info/LICENSE
pycea-0.0.2.dist-info/WHEEL
pycea-0.0.2.dist-info/entry_points.txt
pycea-0.0.2.dist-info/top_level.txt
pycea-0.0.2.dist-info/METADATA
pycea/wrapper.py
pycea/units.py
pycea/isp.py
pycea/separated_Cf.py
pycea/input_cards.py
pycea/__init__.py
pycea/blends.py
pycea/goal.py
pycea/cea.py
pycea/.dylibs/libgfortran.5.dylib
pycea/.dylibs/libquadmath.0.dylib
pycea/.dylibs/libgcc_s.1.1.dylib
pycea/fortran/thermo.inp
pycea/fortran/trans.lib
pycea/fortran/py_cea.cpython-310-darwin.so
pycea/fortran/f.inp
pycea/fortran/thermo.lib
pycea/fortran/trans.inp
pycea/fortran/py_cea.inc
pycea/fortran/temp.dat
