Metadata-Version: 2.1
Name: pycea
Version: 0.0.2
Summary: pycea is a modern Python wrapper for the NASA CEA code.
Author-email: Jiri Kovar <jiri@kovar.cz>
License: GNU GENERAL PUBLIC LICENSE
Project-URL: Homepage, https://pycea.org
Project-URL: Documentation, https://docs.pycea.org
Project-URL: Repository, https://github.com/kovar/pycea
Project-URL: Issues, https://github.com/kovar/pycea/issues
Keywords: NASA,CEA,wrapper,thermodynamics,rocket,propulsion,combustion,chemistry
Classifier: Development Status :: 1 - Planning
Classifier: Intended Audience :: Developers
Classifier: Intended Audience :: Education
Classifier: Intended Audience :: Science/Research
Classifier: License :: OSI Approved :: GNU General Public License v3 (GPLv3)
Classifier: Natural Language :: English
Classifier: Operating System :: OS Independent
Classifier: Programming Language :: Python :: 3.8
Classifier: Programming Language :: Python :: 3.9
Classifier: Programming Language :: Python :: 3.10
Classifier: Programming Language :: Python :: 3.11
Classifier: Topic :: Scientific/Engineering
Requires-Python: >=3.8
License-File: LICENSE
Requires-Dist: numpy (>=1.24)
Provides-Extra: dev
Requires-Dist: pytest ; extra == 'dev'
Requires-Dist: black ; extra == 'dev'
